mypackage/__init__.py
mypackage/module1.py
mypackage/module2.py
mypackage/subpackage/__init__.py
mypackage/subpackage/submodule1.py
mypackage20240516wkh-0.1.dist-info/METADATA
mypackage20240516wkh-0.1.dist-info/WHEEL
mypackage20240516wkh-0.1.dist-info/top_level.txt
mypackage20240516wkh-0.1.dist-info/RECORD
